3fed2dd976ff832859ee__mypyc.cpython-38-darwin.so
checksum_dict/_typing.py
checksum_dict/__init__.py
checksum_dict/_utils.cpython-38-darwin.so
checksum_dict/default.py
checksum_dict/default.cpython-38-darwin.so
checksum_dict/singleton.py
checksum_dict/py.typed
checksum_dict/exceptions.py
checksum_dict/base.cpython-38-darwin.so
checksum_dict/base.py
checksum_dict/_utils.py
checksum_dict-2.1.13.dist-info/RECORD
checksum_dict-2.1.13.dist-info/LICENSE
checksum_dict-2.1.13.dist-info/WHEEL
checksum_dict-2.1.13.dist-info/top_level.txt
checksum_dict-2.1.13.dist-info/METADATA
